{
  "title": "Популярные товары",
  "table": "popular_products",
  "methods": [ "GET" ],
  "params": [
    {
      "title": "Идентификатор",
      "article": "id",
      "type": "int",
      "null": "NO",
      "default": "",
      "display": false,
      "display_type": "number",
      "take_from": null
    },
    {
      "title": "ID Продукта",
      "article": "product_id",
      "type": "int",
      "null": "NO",
      "default": "",
      "display": false,
      "display_type": "string",
      "take_from": null
    }
  ]
}